latest_earthquake/__init__.py
LatestIndonesiaEarthquake-0.0.2.dist-info/LICENSE
LatestIndonesiaEarthquake-0.0.2.dist-info/METADATA
LatestIndonesiaEarthquake-0.0.2.dist-info/WHEEL
LatestIndonesiaEarthquake-0.0.2.dist-info/top_level.txt
LatestIndonesiaEarthquake-0.0.2.dist-info/RECORD
